Workbook

Sheet Products
A1: Product Code | B1: Product Name | C1: Category | D1: Unit Price (RM)
A2: P001 | B2: Wireless Mouse | C2: Electronics | D2: 79.9
A3: P002 | B3: USB-C Hub 7-in-1 | C3: Electronics | D3: 149
A4: P003 | B4: Mechanical Keyboard | C4: Electronics | D4: 249.9
A5: P004 | B5: Monitor Stand | C5: Accessories | D5: 99
A6: P005 | B6: Webcam HD 1080p | C6: Electronics | D6: 129.9
A7: P006 | B7: Desk Lamp LED | C7: Accessories | D7: 59.9
A8: P007 | B8: Ergonomic Chair | C8: Furniture | D8: 899
A9: P008 | B9: Standing Desk | C9: Furniture | D9: 1299
A10: P009 | B10: Notebook A5 3-pack | C10: Stationery | D10: 24.9
A11: P010 | B11: Whiteboard 60x90cm | C11: Accessories | D11: 189

Sheet Sales
A1: Date | B1: Product Code | C1: Product Name | D1: Category | E1: Quantity | F1: Payment Method | G1: Unit Price (RM) | H1: Total (RM)
A2: 46027 | B2: P001 | C2: =VLOOKUP($B2,Products!$A$2:$D$11,2,FALSE) | D2: =VLOOKUP($B2,Products!$A$2:$D$11,3,FALSE) | E2: 12 | F2: Cash | G2: =VLOOKUP($B2,Products!$A$2:$D$11,4,FALSE) | H2: =E2*G2
A3: 46030 | B3: P003 | C3: =VLOOKUP($B3,Products!$A$2:$D$11,2,FALSE) | D3: =VLOOKUP($B3,Products!$A$2:$D$11,3,FALSE) | E3: 5 | F3: Credit Card | G3: =VLOOKUP($B3,Products!$A$2:$D$11,4,FALSE) | H3: =E3*G3
A4: 46037 | B4: P007 | C4: =VLOOKUP($B4,Products!$A$2:$D$11,2,FALSE) | D4: =VLOOKUP($B4,Products!$A$2:$D$11,3,FALSE) | E4: 2 | F4: Bank Transfer | G4: =VLOOKUP($B4,Products!$A$2:$D$11,4,FALSE) | H4: =E4*G4
A5: 46044 | B5: P002 | C5: =VLOOKUP($B5,Products!$A$2:$D$11,2,FALSE) | D5: =VLOOKUP($B5,Products!$A$2:$D$11,3,FALSE) | E5: 10 | F5: Cash | G5: =VLOOKUP($B5,Products!$A$2:$D$11,4,FALSE) | H5: =E5*G5
A6: 46056 | B6: P005 | C6: =VLOOKUP($B6,Products!$A$2:$D$11,2,FALSE) | D6: =VLOOKUP($B6,Products!$A$2:$D$11,3,FALSE) | E6: 8 | F6: Credit Card | G6: =VLOOKUP($B6,Products!$A$2:$D$11,4,FALSE) | H6: =E6*G6
A7: 46063 | B7: P004 | C7: =VLOOKUP($B7,Products!$A$2:$D$11,2,FALSE) | D7: =VLOOKUP($B7,Products!$A$2:$D$11,3,FALSE) | E7: 15 | F7: Cash | G7: =VLOOKUP($B7,Products!$A$2:$D$11,4,FALSE) | H7: =E7*G7
A8: 46071 | B8: P008 | C8: =VLOOKUP($B8,Products!$A$2:$D$11,2,FALSE) | D8: =VLOOKUP($B8,Products!$A$2:$D$11,3,FALSE) | E8: 1 | F8: Bank Transfer | G8: =VLOOKUP($B8,Products!$A$2:$D$11,4,FALSE) | H8: =E8*G8
A9: 46078 | B9: P009 | C9: =VLOOKUP($B9,Products!$A$2:$D$11,2,FALSE) | D9: =VLOOKUP($B9,Products!$A$2:$D$11,3,FALSE) | E9: 20 | F9: Cash | G9: =VLOOKUP($B9,Products!$A$2:$D$11,4,FALSE) | H9: =E9*G9
A10: 46083 | B10: P006 | C10: =VLOOKUP($B10,Products!$A$2:$D$11,2,FALSE) | D10: =VLOOKUP($B10,Products!$A$2:$D$11,3,FALSE) | E10: 10 | F10: Cash | G10: =VLOOKUP($B10,Products!$A$2:$D$11,4,FALSE) | H10: =E10*G10
A11: 46090 | B11: P001 | C11: =VLOOKUP($B11,Products!$A$2:$D$11,2,FALSE) | D11: =VLOOKUP($B11,Products!$A$2:$D$11,3,FALSE) | E11: 15 | F11: Credit Card | G11: =VLOOKUP($B11,Products!$A$2:$D$11,4,FALSE) | H11: =E11*G11
A12: 46095 | B12: P010 | C12: =VLOOKUP($B12,Products!$A$2:$D$11,2,FALSE) | D12: =VLOOKUP($B12,Products!$A$2:$D$11,3,FALSE) | E12: 6 | F12: Bank Transfer | G12: =VLOOKUP($B12,Products!$A$2:$D$11,4,FALSE) | H12: =E12*G12
A13: 46101 | B13: P003 | C13: =VLOOKUP($B13,Products!$A$2:$D$11,2,FALSE) | D13: =VLOOKUP($B13,Products!$A$2:$D$11,3,FALSE) | E13: 8 | F13: Credit Card | G13: =VLOOKUP($B13,Products!$A$2:$D$11,4,FALSE) | H13: =E13*G13
... A26: 46198 | B26: P005 | C26: =VLOOKUP($B26,Products!$A$2:$D$11,2,FALSE) | D26: =VLOOKUP($B26,Products!$A$2:$D$11,3,FALSE) | E26: 9 | F26: Cash | G26: =VLOOKUP($B26,Products!$A$2:$D$11,4,FALSE) | H26: =E26*G26
A27: TOTAL | E27: =SUM(E2:E26) | H27: =SUM(H2:H26)

Sheet Monthly Summary
A1: Month | B1: Transactions | C1: Total Qty Sold | D1: Total Revenue (RM) | E1: Average Order Value (RM)
A2: January 2026 | B2: =COUNTIFS(Sales!$A$2:$A$26,">="&DATE(2026,1,1),Sales!$A$2:$A$26,"<"&DATE(2026,2,1)) | C2: =SUMPRODUCT((Sales!$A$2:$A$26>=DATE(2026,1,1))*(Sales!$A$2:$A$26<DATE(2026,2,1))*Sales!$E$2:$E$26) | D2: =SUMPRODUCT((Sales!$A$2:$A$26>=DATE(2026,1,1))*(Sales!$A$2:$A$26<DATE(2026,2,1))*Sales!$H$2:$H$26) | E2: =IFERROR(D2/B2,0)
A3: February 2026 | B3: =COUNTIFS(Sales!$A$2:$A$26,">="&DATE(2026,2,1),Sales!$A$2:$A$26,"<"&DATE(2026,3,1)) | C3: =SUMPRODUCT((Sales!$A$2:$A$26>=DATE(2026,2,1))*(Sales!$A$2:$A$26<DATE(2026,3,1))*Sales!$E$2:$E$26) | D3: =SUMPRODUCT((Sales!$A$2:$A$26>=DATE(2026,2,1))*(Sales!$A$2:$A$26<DATE(2026,3,1))*Sales!$H$2:$H$26) | E3: =IFERROR(D3/B3,0)
A4: March 2026 | B4: =COUNTIFS(Sales!$A$2:$A$26,">="&DATE(2026,3,1),Sales!$A$2:$A$26,"<"&DATE(2026,4,1)) | C4: =SUMPRODUCT((Sales!$A$2:$A$26>=DATE(2026,3,1))*(Sales!$A$2:$A$26<DATE(2026,4,1))*Sales!$E$2:$E$26) | D4: =SUMPRODUCT((Sales!$A$2:$A$26>=DATE(2026,3,1))*(Sales!$A$2:$A$26<DATE(2026,4,1))*Sales!$H$2:$H$26) | E4: =IFERROR(D4/B4,0)
A5: April 2026 | B5: =COUNTIFS(Sales!$A$2:$A$26,">="&DATE(2026,4,1),Sales!$A$2:$A$26,"<"&DATE(2026,5,1)) | C5: =SUMPRODUCT((Sales!$A$2:$A$26>=DATE(2026,4,1))*(Sales!$A$2:$A$26<DATE(2026,5,1))*Sales!$E$2:$E$26) | D5: =SUMPRODUCT((Sales!$A$2:$A$26>=DATE(2026,4,1))*(Sales!$A$2:$A$26<DATE(2026,5,1))*Sales!$H$2:$H$26) | E5: =IFERROR(D5/B5,0)
A6: May 2026 | B6: =COUNTIFS(Sales!$A$2:$A$26,">="&DATE(2026,5,1),Sales!$A$2:$A$26,"<"&DATE(2026,6,1)) | C6: =SUMPRODUCT((Sales!$A$2:$A$26>=DATE(2026,5,1))*(Sales!$A$2:$A$26<DATE(2026,6,1))*Sales!$E$2:$E$26) | D6: =SUMPRODUCT((Sales!$A$2:$A$26>=DATE(2026,5,1))*(Sales!$A$2:$A$26<DATE(2026,6,1))*Sales!$H$2:$H$26) | E6: =IFERROR(D6/B6,0)
A7: June 2026 | B7: =COUNTIFS(Sales!$A$2:$A$26,">="&DATE(2026,6,1),Sales!$A$2:$A$26,"<"&DATE(2026,7,1)) | C7: =SUMPRODUCT((Sales!$A$2:$A$26>=DATE(2026,6,1))*(Sales!$A$2:$A$26<DATE(2026,7,1))*Sales!$E$2:$E$26) | D7: =SUMPRODUCT((Sales!$A$2:$A$26>=DATE(2026,6,1))*(Sales!$A$2:$A$26<DATE(2026,7,1))*Sales!$H$2:$H$26) | E7: =IFERROR(D7/B7,0)
A8: TOTAL | B8: =SUM(B2:B7) | C8: =SUM(C2:C7) | D8: =SUM(D2:D7) | E8: =IFERROR(D8/B8,0)

Sheet Category Summary
A1: Category | B1: Products | C1: Total Qty Sold | D1: Total Revenue (RM) | E1: % of Total Revenue
A2: Electronics | B2: =COUNTIF(Products!$C$2:$C$11,A2) | C2: =SUMIF(Sales!$D$2:$D$26,A2,Sales!$E$2:$E$26) | D2: =SUMIF(Sales!$D$2:$D$26,A2,Sales!$H$2:$H$26) | E2: =IFERROR(D2/D$6,0)
A3: Accessories | B3: =COUNTIF(Products!$C$2:$C$11,A3) | C3: =SUMIF(Sales!$D$2:$D$26,A3,Sales!$E$2:$E$26) | D3: =SUMIF(Sales!$D$2:$D$26,A3,Sales!$H$2:$H$26) | E3: =IFERROR(D3/D$6,0)
A4: Furniture | B4: =COUNTIF(Products!$C$2:$C$11,A4) | C4: =SUMIF(Sales!$D$2:$D$26,A4,Sales!$E$2:$E$26) | D4: =SUMIF(Sales!$D$2:$D$26,A4,Sales!$H$2:$H$26) | E4: =IFERROR(D4/D$6,0)
A5: Stationery | B5: =COUNTIF(Products!$C$2:$C$11,A5) | C5: =SUMIF(Sales!$D$2:$D$26,A5,Sales!$E$2:$E$26) | D5: =SUMIF(Sales!$D$2:$D$26,A5,Sales!$H$2:$H$26) | E5: =IFERROR(D5/D$6,0)
A6: TOTAL | B6: =SUM(B2:B5) | C6: =SUM(C2:C5) | D6: =SUM(D2:D5) | E6: =SUM(E2:E5)

Sheet Payment Summary
A1: Payment Method | B1: Transactions | C1: Total Qty | D1: Total Revenue (RM) | E1: % of Revenue
A2: Cash | B2: =COUNTIF(Sales!$F$2:$F$26,A2) | C2: =SUMIF(Sales!$F$2:$F$26,A2,Sales!$E$2:$E$26) | D2: =SUMIF(Sales!$F$2:$F$26,A2,Sales!$H$2:$H$26) | E2: =IFERROR(D2/D$5,0)
A3: Credit Card | B3: =COUNTIF(Sales!$F$2:$F$26,A3) | C3: =SUMIF(Sales!$F$2:$F$26,A3,Sales!$E$2:$E$26) | D3: =SUMIF(Sales!$F$2:$F$26,A3,Sales!$H$2:$H$26) | E3: =IFERROR(D3/D$5,0)
A4: Bank Transfer | B4: =COUNTIF(Sales!$F$2:$F$26,A4) | C4: =SUMIF(Sales!$F$2:$F$26,A4,Sales!$E$2:$E$26) | D4: =SUMIF(Sales!$F$2:$F$26,A4,Sales!$H$2:$H$26) | E4: =IFERROR(D4/D$5,0)
A5: TOTAL | B5: =SUM(B2:B4) | C5: =SUM(C2:C4) | D5: =SUM(D2:D4) | E5: =SUM(E2:E4)
